<?xml version='1.0'?>
<ns2:test-suite xmlns:ns2='urn:model.allure.qatools.yandex.ru' start='1587133776793' stop='1587133874323'>
    <name>login-logout:</name>
    <title>login-logout:</title>
    <test-cases>
        <test-case start='1587133776795' status='passed' stop='1587133846446'>
            <name>testing login feature</name>
            <title>testing login feature</title>
            <labels/>
            <parameters/>
            <steps>
                <step start='1587133780432' status='passed' stop='1587133784312'>
                    <name>I am on page "/"</name>
                    <title>I am on page "/"</title>
                    <attachments/>
                    <steps/>
                </step>
                <step start='1587133784312' status='passed' stop='1587133784542'>
                    <name>I click "Login"</name>
                    <title>I click "Login"</title>
                    <attachments/>
                    <steps/>
                </step>
                <step start='1587133784543' status='passed' stop='1587133784962'>
                    <name>I fill field "Username", "gpichmann0"</name>
                    <title>I fill field "Username", "gpichmann0"</title>
                    <attachments/>
                    <steps/>
                </step>
                <step start='1587133784962' status='passed' stop='1587133785063'>
                    <name>I click "#sign-in-btn"</name>
                    <title>I click "#sign-in-btn"</title>
                    <attachments/>
                    <steps/>
                </step>
                <step start='1587133785063' status='passed' stop='1587133792674'>
                    <name>I am on page "/drivers"</name>
                    <title>I am on page "/drivers"</title>
                    <attachments/>
                    <steps/>
                </step>
                <step start='1587133792674' status='passed' stop='1587133817362'>
                    <name>I see element "#logo"</name>
                    <title>I see element "#logo"</title>
                    <attachments/>
                    <steps/>
                </step>
                <step start='1587133817362' status='passed' stop='1587133817451'>
                    <name>I click "#logo"</name>
                    <title>I click "#logo"</title>
                    <attachments/>
                    <steps/>
                </step>
                <step start='1587133817452' status='passed' stop='1587133821774'>
                    <name>I am on page "/drivers"</name>
                    <title>I am on page "/drivers"</title>
                    <attachments/>
                    <steps/>
                </step>
                <step start='1587133821774' status='passed' stop='1587133846159'>
                    <name>I click "Grady Pichmann"</name>
                    <title>I click "Grady Pichmann"</title>
                    <attachments/>
                    <steps/>
                </step>
                <step start='1587133846159' status='passed' stop='1587133846445'>
                    <name>I click "Log Out"</name>
                    <title>I click "Log Out"</title>
                    <attachments/>
                    <steps/>
                </step>
            </steps>
            <attachments/>
        </test-case>
        <test-case start='1587133846739' status='passed' stop='1587133862161'>
            <name>testing logout feature</name>
            <title>testing logout feature</title>
            <labels/>
            <parameters/>
            <steps>
                <step start='1587133850287' status='passed' stop='1587133854089'>
                    <name>I am on page "/"</name>
                    <title>I am on page "/"</title>
                    <attachments/>
                    <steps/>
                </step>
                <step start='1587133854089' status='passed' stop='1587133854324'>
                    <name>I click "Login"</name>
                    <title>I click "Login"</title>
                    <attachments/>
                    <steps/>
                </step>
                <step start='1587133854324' status='passed' stop='1587133854904'>
                    <name>I fill field "Username", "gpichmann0"</name>
                    <title>I fill field "Username", "gpichmann0"</title>
                    <attachments/>
                    <steps/>
                </step>
                <step start='1587133854904' status='passed' stop='1587133855015'>
                    <name>I click "#sign-in-btn"</name>
                    <title>I click "#sign-in-btn"</title>
                    <attachments/>
                    <steps/>
                </step>
                <step start='1587133855015' status='passed' stop='1587133858744'>
                    <name>I click "Grady Pichmann"</name>
                    <title>I click "Grady Pichmann"</title>
                    <attachments/>
                    <steps/>
                </step>
                <step start='1587133858744' status='passed' stop='1587133859101'>
                    <name>I click "Log Out"</name>
                    <title>I click "Log Out"</title>
                    <attachments/>
                    <steps/>
                </step>
                <step start='1587133859102' status='passed' stop='1587133859231'>
                    <name>I see element "#logo"</name>
                    <title>I see element "#logo"</title>
                    <attachments/>
                    <steps/>
                </step>
                <step start='1587133859231' status='passed' stop='1587133859387'>
                    <name>I click "#logo"</name>
                    <title>I click "#logo"</title>
                    <attachments/>
                    <steps/>
                </step>
                <step start='1587133859387' status='passed' stop='1587133862161'>
                    <name>I am on page "/"</name>
                    <title>I am on page "/"</title>
                    <attachments/>
                    <steps/>
                </step>
            </steps>
            <attachments/>
        </test-case>
        <test-case start='1587133862381' status='passed' stop='1587133874082'>
            <name>testing bad login</name>
            <title>testing bad login</title>
            <labels/>
            <parameters/>
            <steps>
                <step start='1587133866097' status='passed' stop='1587133869825'>
                    <name>I am on page "/"</name>
                    <title>I am on page "/"</title>
                    <attachments/>
                    <steps/>
                </step>
                <step start='1587133869825' status='passed' stop='1587133870116'>
                    <name>I click "Login"</name>
                    <title>I click "Login"</title>
                    <attachments/>
                    <steps/>
                </step>
                <step start='1587133870116' status='passed' stop='1587133870681'>
                    <name>I fill field "Username", "manpolice"</name>
                    <title>I fill field "Username", "manpolice"</title>
                    <attachments/>
                    <steps/>
                </step>
                <step start='1587133870681' status='passed' stop='1587133870836'>
                    <name>I click "#sign-in-btn"</name>
                    <title>I click "#sign-in-btn"</title>
                    <attachments/>
                    <steps/>
                </step>
                <step start='1587133870836' status='passed' stop='1587133871018'>
                    <name>I see "User not found!"</name>
                    <title>I see "User not found!"</title>
                    <attachments/>
                    <steps/>
                </step>
                <step start='1587133871018' status='passed' stop='1587133871139'>
                    <name>I click "#logo"</name>
                    <title>I click "#logo"</title>
                    <attachments/>
                    <steps/>
                </step>
                <step start='1587133871139' status='passed' stop='1587133874082'>
                    <name>I am on page "/"</name>
                    <title>I am on page "/"</title>
                    <attachments/>
                    <steps/>
                </step>
            </steps>
            <attachments/>
        </test-case>
    </test-cases>
</ns2:test-suite>